krait/__init__.py
krait/__main__.py
krait/cli.py
krait/main.py
krait/lib/__init__.py
krait/lib/abc.py
krait/lib/files.py
krait/lib/renderers.py
krait/lib/plugins/__init__.py
krait/lib/plugins/automations.py
krait/lib/plugins/base_plugin.py
krait/lib/plugins/help_links.py
krait/lib/plugins/linters.py
krait/lib/plugins/project_frameworks.py
krait/lib/plugins/test_frameworks.py
krait/lib/plugins/type_checkers.py
krait/lib/plugins/vcs.py
krait/templates/.gitignore.jinja2
krait/templates/azure-azure-pipeline.yml.jinja2
krait/templates/base-makefile.jinja2
krait/templates/click-main.py.jinja2
krait/templates/flake8-makefile.jinja2
krait/templates/flake8-setup.cfg.jinja2
krait/templates/flask-.env.example.jinja2
krait/templates/flask-api.py.jinja2
krait/templates/flask-app.py.jinja2
krait/templates/flask-config.py.jinja2
krait/templates/flask-docker-compose.yaml.jinja2
krait/templates/flask-dockerfile.jinja2
krait/templates/flask-makefile.jinja2
krait/templates/flask-readme.jinja2
krait/templates/flask-root.py.jinja2
krait/templates/flask-routes.py.jinja2
krait/templates/flask-run.sh.jinja2
krait/templates/gha-build.yml.jinja2
krait/templates/library-lib.py.jinja2
krait/templates/mypy-makefile.jinja2
krait/templates/mypy-setup.cfg.jinja2
krait/templates/pytest-click-cli_test.py.jinja2
krait/templates/pytest-flask-app_test.py.jinja2
krait/templates/pytest-library-lib_test.py.jinja2
krait/templates/pytest-makefile.jinja2
krait/templates/pytest-setup.cfg.jinja2
krait/templates/setup.py.jinja2
krait/utils/__init__.py
krait/utils/config.py
krait/utils/plugins.py
krait/utils/templates.py
krait/utils/update.py
krait-0.7.4.dist-info/LICENSE
krait-0.7.4.dist-info/METADATA
krait-0.7.4.dist-info/WHEEL
krait-0.7.4.dist-info/entry_points.txt
krait-0.7.4.dist-info/top_level.txt
krait-0.7.4.dist-info/RECORD
