Metadata-Version: 2.1
Name: krait
Version: 0.7.4
Summary: A Python CLI tool to create new python projects.
Home-page: https://github.com/taliamax/krait
Author: Natalia Maximo
Author-email: iam@natalia.dev
License: Apache Software License
Keywords: cli project startup
Platform: UNKNOWN
Classifier: Development Status :: 4 - Beta
Classifier: Environment :: Console
Classifier: Intended Audience :: Developers
Classifier: License :: OSI Approved :: Apache Software License
Classifier: Operating System :: OS Independent
Classifier: Programming Language :: Python :: 3
Classifier: Programming Language :: Python :: 3.7
Classifier: Programming Language :: Python :: 3.8
Classifier: Programming Language :: Python :: 3.9
Classifier: Programming Language :: Python :: 3.10
Classifier: Topic :: Utilities
Classifier: Typing :: Typed
Requires-Python: >=3.7
License-File: LICENSE
Requires-Dist: click (>=8.0)
Requires-Dist: jinja2
Requires-Dist: pydeepmerge
Requires-Dist: gitpython
Provides-Extra: tests
Requires-Dist: pytest-cov ; extra == 'tests'
Requires-Dist: flake8 ; extra == 'tests'
Requires-Dist: mypy ; extra == 'tests'
Requires-Dist: pytest ; extra == 'tests'
Requires-Dist: types-setuptools ; extra == 'tests'
